DyLoPro/DynamicLogPlotting.py
DyLoPro/__init__.py
DyLoPro/check_args.py
DyLoPro/plot_components.py
DyLoPro/plotting_utils.py
DyLoPro/preprocess_utils.py
DyLoPro/univariate_plots.py
DyLoPro/validate_methods.py
DyLoPro-0.1.1.dist-info/AUTHORS.md
DyLoPro-0.1.1.dist-info/LICENSE
DyLoPro-0.1.1.dist-info/METADATA
DyLoPro-0.1.1.dist-info/WHEEL
DyLoPro-0.1.1.dist-info/top_level.txt
DyLoPro-0.1.1.dist-info/RECORD
