Metadata-Version: 2.1
Name: DyLoPro
Version: 0.1.1
Summary: Dynamic Log Profiling package
Home-page: https://github.com/BrechtWts/DyLoPro
Author: Brecht Wuyts 
Author-email: brecht.wuyts@kuleuven.be
License: GNU General Public License v3
Keywords: DyLoPro
Classifier: Development Status :: 2 - Pre-Alpha
Classifier: Intended Audience :: Developers
Classifier: License :: OSI Approved :: GNU General Public License v3 (GPLv3)
Classifier: Natural Language :: English
Classifier: Programming Language :: Python :: 3
Classifier: Programming Language :: Python :: 3.6
Classifier: Programming Language :: Python :: 3.7
Classifier: Programming Language :: Python :: 3.8
Classifier: Programming Language :: Python :: 3.9
Classifier: Programming Language :: Python :: 3.10
Classifier: Topic :: Scientific/Engineering
Classifier: Topic :: Scientific/Engineering :: Artificial Intelligence
Classifier: Topic :: Scientific/Engineering :: Visualization
Requires-Python: >=3.6
License-File: LICENSE
License-File: AUTHORS.md
Requires-Dist: matplotlib (>=3.7.1)
Requires-Dist: numpy (>=1.21.5)
Requires-Dist: pandas (>=2.0.2)
Requires-Dist: tqdm (>=4.63.0)
